onionprobe/__init__.py
onionprobe/app.py
onionprobe/certificate.py
onionprobe/config.py
onionprobe/descriptor.py
onionprobe/http.py
onionprobe/init.py
onionprobe/logger.py
onionprobe/main.py
onionprobe/metrics.py
onionprobe/prober.py
onionprobe/teardown.py
onionprobe/time.py
onionprobe/tls.py
onionprobe/tor.py
onionprobe-1.4.1.data/data/share/onionprobe/configs/real-world-onion-sites.yaml
onionprobe-1.4.1.data/data/share/onionprobe/configs/securedrop.yaml
onionprobe-1.4.1.data/data/share/onionprobe/configs/tor.yaml
onionprobe-1.4.1.data/data/share/onionprobe/examples/real-world-onion-sites.py
onionprobe-1.4.1.data/data/share/onionprobe/examples/securedrop.py
onionprobe-1.4.1.data/data/share/onionprobe/examples/tpo.py
onionprobe-1.4.1.dist-info/licenses/LICENSE
onionprobe-1.4.1.dist-info/METADATA
onionprobe-1.4.1.dist-info/WHEEL
onionprobe-1.4.1.dist-info/entry_points.txt
onionprobe-1.4.1.dist-info/top_level.txt
onionprobe-1.4.1.dist-info/RECORD
